mudbrick/__init__.py
mudbrick/app.py
mudbrick/commands.py
mudbrick/templates.py
mudbrick-0.0.2.dist-info/LICENSE
mudbrick-0.0.2.dist-info/METADATA
mudbrick-0.0.2.dist-info/WHEEL
mudbrick-0.0.2.dist-info/entry_points.txt
mudbrick-0.0.2.dist-info/top_level.txt
mudbrick-0.0.2.dist-info/RECORD
