Metadata-Version: 2.1
Name: mudbrick
Version: 0.0.2
Summary: Mudbrick Builds a flask application factory boilerplate.
Home-page: https://github.com/owen-eternal/flask-bucket
Author: Owen O. Phakade
Author-email: olwethuphakade89@gmail.com
License: BSD
Platform: UNKNOWN
Classifier: Environment :: Web Environment
Classifier: Intended Audience :: Developers
Classifier: License :: OSI Approved :: BSD License
Classifier: Operating System :: OS Independent
Classifier: Programming Language :: Python
Classifier: Topic :: Internet :: WWW/HTTP :: Dynamic Content
Classifier: Topic :: Software Development :: Libraries :: Python Modules
Requires-Dist: Click
Requires-Dist: flask
Requires-Dist: flask-Sqlalchemy
